screenwriter/__init__.py
screenwriter/echo.py
screenwriter-1.0.4.dist-info/LICENSE
screenwriter-1.0.4.dist-info/METADATA
screenwriter-1.0.4.dist-info/WHEEL
screenwriter-1.0.4.dist-info/top_level.txt
screenwriter-1.0.4.dist-info/RECORD
