Metadata-Version: 2.1
Name: screenwriter
Version: 1.0.4
Summary: python library for writing progress texts, echo messages, warnings and errors to standard output
Home-page: https://github.com/satapathy/pypi-screenwriter
Author: S Satapathy
Author-email: shubhakant.satapathy@gmail.com
License: UNKNOWN
Platform: UNKNOWN
Classifier: Programming Language :: Python :: 3
Classifier: License :: OSI Approved :: MIT License
Classifier: Operating System :: OS Independent
